compas_cra/__init__.py
compas_cra/__main__.py
compas_cra/algorithms/__init__.py
compas_cra/algorithms/interfaces_numpy.py
compas_cra/datastructures/__init__.py
compas_cra/datastructures/cra_assembly.py
compas_cra/equilibrium/__init__.py
compas_cra/equilibrium/cra_helper.py
compas_cra/equilibrium/cra_penalty_pyomo.py
compas_cra/equilibrium/cra_pyomo.py
compas_cra/equilibrium/pyomo_helper.py
compas_cra/equilibrium/rbe_pyomo.py
compas_cra/geometry/__init__.py
compas_cra/geometry/arch.py
compas_cra/viewers/__init__.py
compas_cra/viewers/cra_view.py
compas_cra-0.4.0.dist-info/LICENSE
compas_cra-0.4.0.dist-info/METADATA
compas_cra-0.4.0.dist-info/WHEEL
compas_cra-0.4.0.dist-info/top_level.txt
compas_cra-0.4.0.dist-info/RECORD
